{
    "id": "altosz_grass",
    "classes": [
        {
            "privateField": {
                "d": 0,
                "DRelative": 0,
                "SRelative": 0,
                "total": 0,
                "s": 0
            },
            "protectedConstructorParameter": {
                "d": 0,
                "DRelative": 0,
                "SRelative": 0,
                "total": 0,
                "s": 0
            },
            "protectedMethodParameter": {
                "d": 3,
                "DRelative": 1.0,
                "SRelative": 0.0,
                "total": 3,
                "s": 0
            },
            "privateMethodParameter": {
                "d": 0,
                "DRelative": 0,
                "SRelative": 0,
                "total": 0,
                "s": 0
            },
            "privateConstructorParameter": {
                "d": 0,
                "DRelative": 0,
                "SRelative": 0,
                "total": 0,
                "s": 0
            },
            "pureTypeSystemPrivateMethods": {
                "d": 0,
                "DRelative": 0,
                "SRelative": 0,
                "total": 0,
                "s": 0
            },
            "privateMethodReturn": {
                "d": 0,
                "DRelative": 0,
                "SRelative": 0,
                "total": 0,
                "s": 0
            },
            "location": "/opt/groovonomics/temp/altosz_grass/src/groovy/CompassCompile.groovy",
            "localVariable": {
                "d": 6,
                "DRelative": 1.0,
                "SRelative": 0.0,
                "total": 6,
                "s": 0
            },
            "pureTypeSystemProtectedConstructors": {
                "d": 0,
                "DRelative": 0,
                "SRelative": 0,
                "total": 0,
                "s": 0
            },
            "isScript": false,
            "publicField": {
                "d": 0,
                "DRelative": 0,
                "SRelative": 0,
                "total": 0,
                "s": 0
            },
            "pureTypeSystemProtectedMethods": {
                "d": 0,
                "DRelative": 0,
                "SRelative": 0,
                "total": 0,
                "s": 0
            },
            "numberOfPublicConstructors": 0,
            "className": "CompassCompile",
            "pureTypeSystemPrivateConstructors": {
                "d": 0,
                "DRelative": 0,
                "SRelative": 0,
                "total": 0,
                "s": 0
            },
            "protectedMethodReturn": {
                "d": 0,
                "DRelative": 0.0,
                "SRelative": 1.0,
                "total": 1,
                "s": 1
            },
            "publicMethodParameter": {
                "d": 3,
                "DRelative": 1.0,
                "SRelative": 0.0,
                "total": 3,
                "s": 0
            },
            "pureTypeSystemPublicMethods": {
                "d": 0,
                "DRelative": 0,
                "SRelative": 0,
                "total": 0,
                "s": 0
            },
            "publicConstructorParameter": {
                "d": 0,
                "DRelative": 0,
                "SRelative": 0,
                "total": 0,
                "s": 0
            },
            "publicMethodReturn": {
                "d": 0,
                "DRelative": 0.0,
                "SRelative": 1.0,
                "total": 1,
                "s": 1
            },
            "protectedField": {
                "d": 0,
                "DRelative": 0,
                "SRelative": 0,
                "total": 0,
                "s": 0
            },
            "numberOfPrivateConstructors": 0,
            "pureTypeSystemPublicConstructors": {
                "d": 0,
                "DRelative": 0,
                "SRelative": 0,
                "total": 0,
                "s": 0
            },
            "numberOfProtectedConstructors": 0
        },
        {
            "privateField": {
                "d": 0,
                "DRelative": 0,
                "SRelative": 0,
                "total": 0,
                "s": 0
            },
            "protectedConstructorParameter": {
                "d": 0,
                "DRelative": 0,
                "SRelative": 0,
                "total": 0,
                "s": 0
            },
            "protectedMethodParameter": {
                "d": 0,
                "DRelative": 0,
                "SRelative": 0,
                "total": 0,
                "s": 0
            },
            "privateMethodParameter": {
                "d": 0,
                "DRelative": 0,
                "SRelative": 0,
                "total": 0,
                "s": 0
            },
            "privateConstructorParameter": {
                "d": 0,
                "DRelative": 0,
                "SRelative": 0,
                "total": 0,
                "s": 0
            },
            "pureTypeSystemPrivateMethods": {
                "d": 0,
                "DRelative": 0,
                "SRelative": 0,
                "total": 0,
                "s": 0
            },
            "privateMethodReturn": {
                "d": 0,
                "DRelative": 0,
                "SRelative": 0,
                "total": 0,
                "s": 0
            },
            "location": "/opt/groovonomics/temp/altosz_grass/src/groovy/CompassGridImg.groovy",
            "localVariable": {
                "d": 1,
                "DRelative": 1.0,
                "SRelative": 0.0,
                "total": 1,
                "s": 0
            },
            "pureTypeSystemProtectedConstructors": {
                "d": 0,
                "DRelative": 0,
                "SRelative": 0,
                "total": 0,
                "s": 0
            },
            "isScript": false,
            "publicField": {
                "d": 0,
                "DRelative": 0,
                "SRelative": 0,
                "total": 0,
                "s": 0
            },
            "pureTypeSystemProtectedMethods": {
                "d": 0,
                "DRelative": 0,
                "SRelative": 0,
                "total": 0,
                "s": 0
            },
            "numberOfPublicConstructors": 0,
            "className": "CompassGridImg",
            "pureTypeSystemPrivateConstructors": {
                "d": 0,
                "DRelative": 0,
                "SRelative": 0,
                "total": 0,
                "s": 0
            },
            "protectedMethodReturn": {
                "d": 0,
                "DRelative": 0,
                "SRelative": 0,
                "total": 0,
                "s": 0
            },
            "publicMethodParameter": {
                "d": 3,
                "DRelative": 1.0,
                "SRelative": 0.0,
                "total": 3,
                "s": 0
            },
            "pureTypeSystemPublicMethods": {
                "d": 0,
                "DRelative": 0,
                "SRelative": 0,
                "total": 0,
                "s": 0
            },
            "publicConstructorParameter": {
                "d": 0,
                "DRelative": 0,
                "SRelative": 0,
                "total": 0,
                "s": 0
            },
            "publicMethodReturn": {
                "d": 0,
                "DRelative": 0.0,
                "SRelative": 1.0,
                "total": 1,
                "s": 1
            },
            "protectedField": {
                "d": 0,
                "DRelative": 0,
                "SRelative": 0,
                "total": 0,
                "s": 0
            },
            "numberOfPrivateConstructors": 0,
            "pureTypeSystemPublicConstructors": {
                "d": 0,
                "DRelative": 0,
                "SRelative": 0,
                "total": 0,
                "s": 0
            },
            "numberOfProtectedConstructors": 0
        },
        {
            "privateField": {
                "d": 0,
                "DRelative": 0,
                "SRelative": 0,
                "total": 0,
                "s": 0
            },
            "protectedConstructorParameter": {
                "d": 0,
                "DRelative": 0,
                "SRelative": 0,
                "total": 0,
                "s": 0
            },
            "protectedMethodParameter": {
                "d": 0,
                "DRelative": 0,
                "SRelative": 0,
                "total": 0,
                "s": 0
            },
            "privateMethodParameter": {
                "d": 0,
                "DRelative": 0,
                "SRelative": 0,
                "total": 0,
                "s": 0
            },
            "privateConstructorParameter": {
                "d": 0,
                "DRelative": 0,
                "SRelative": 0,
                "total": 0,
                "s": 0
            },
            "pureTypeSystemPrivateMethods": {
                "d": 0,
                "DRelative": 0,
                "SRelative": 0,
                "total": 0,
                "s": 0
            },
            "privateMethodReturn": {
                "d": 0,
                "DRelative": 0,
                "SRelative": 0,
                "total": 0,
                "s": 0
            },
            "location": "/opt/groovonomics/temp/altosz_grass/grails-app/conf/GrassConfig.groovy",
            "localVariable": {
                "d": 0,
                "DRelative": 0,
                "SRelative": 0,
                "total": 0,
                "s": 0
            },
            "pureTypeSystemProtectedConstructors": {
                "d": 0,
                "DRelative": 0,
                "SRelative": 0,
                "total": 0,
                "s": 0
            },
            "isScript": true,
            "publicField": {
                "d": 0,
                "DRelative": 0,
                "SRelative": 0,
                "total": 0,
                "s": 0
            },
            "pureTypeSystemProtectedMethods": {
                "d": 0,
                "DRelative": 0,
                "SRelative": 0,
                "total": 0,
                "s": 0
            },
            "numberOfPublicConstructors": 2,
            "className": "script1378432037098",
            "pureTypeSystemPrivateConstructors": {
                "d": 0,
                "DRelative": 0,
                "SRelative": 0,
                "total": 0,
                "s": 0
            },
            "protectedMethodReturn": {
                "d": 0,
                "DRelative": 0,
                "SRelative": 0,
                "total": 0,
                "s": 0
            },
            "publicMethodParameter": {
                "d": 0,
                "DRelative": 0.0,
                "SRelative": 1.0,
                "total": 1,
                "s": 1
            },
            "pureTypeSystemPublicMethods": {
                "d": 0,
                "DRelative": 0.0,
                "SRelative": 1.0,
                "total": 1,
                "s": 1
            },
            "publicConstructorParameter": {
                "d": 0,
                "DRelative": 0.0,
                "SRelative": 1.0,
                "total": 1,
                "s": 1
            },
            "publicMethodReturn": {
                "d": 1,
                "DRelative": 0.5,
                "SRelative": 0.5,
                "total": 2,
                "s": 1
            },
            "protectedField": {
                "d": 0,
                "DRelative": 0,
                "SRelative": 0,
                "total": 0,
                "s": 0
            },
            "numberOfPrivateConstructors": 0,
            "pureTypeSystemPublicConstructors": {
                "d": 0,
                "DRelative": 0.0,
                "SRelative": 1.0,
                "total": 1,
                "s": 1
            },
            "numberOfProtectedConstructors": 0
        },
        {
            "privateField": {
                "d": 0,
                "DRelative": 0,
                "SRelative": 0,
                "total": 0,
                "s": 0
            },
            "protectedConstructorParameter": {
                "d": 0,
                "DRelative": 0,
                "SRelative": 0,
                "total": 0,
                "s": 0
            },
            "protectedMethodParameter": {
                "d": 0,
                "DRelative": 0,
                "SRelative": 0,
                "total": 0,
                "s": 0
            },
            "privateMethodParameter": {
                "d": 0,
                "DRelative": 0,
                "SRelative": 0,
                "total": 0,
                "s": 0
            },
            "privateConstructorParameter": {
                "d": 0,
                "DRelative": 0,
                "SRelative": 0,
                "total": 0,
                "s": 0
            },
            "pureTypeSystemPrivateMethods": {
                "d": 0,
                "DRelative": 0,
                "SRelative": 0,
                "total": 0,
                "s": 0
            },
            "privateMethodReturn": {
                "d": 0,
                "DRelative": 0,
                "SRelative": 0,
                "total": 0,
                "s": 0
            },
            "location": "/opt/groovonomics/temp/altosz_grass/grails-app/conf/DataSource.groovy",
            "localVariable": {
                "d": 0,
                "DRelative": 0,
                "SRelative": 0,
                "total": 0,
                "s": 0
            },
            "pureTypeSystemProtectedConstructors": {
                "d": 0,
                "DRelative": 0,
                "SRelative": 0,
                "total": 0,
                "s": 0
            },
            "isScript": true,
            "publicField": {
                "d": 0,
                "DRelative": 0,
                "SRelative": 0,
                "total": 0,
                "s": 0
            },
            "pureTypeSystemProtectedMethods": {
                "d": 0,
                "DRelative": 0,
                "SRelative": 0,
                "total": 0,
                "s": 0
            },
            "numberOfPublicConstructors": 2,
            "className": "script1378432040231",
            "pureTypeSystemPrivateConstructors": {
                "d": 0,
                "DRelative": 0,
                "SRelative": 0,
                "total": 0,
                "s": 0
            },
            "protectedMethodReturn": {
                "d": 0,
                "DRelative": 0,
                "SRelative": 0,
                "total": 0,
                "s": 0
            },
            "publicMethodParameter": {
                "d": 0,
                "DRelative": 0.0,
                "SRelative": 1.0,
                "total": 1,
                "s": 1
            },
            "pureTypeSystemPublicMethods": {
                "d": 0,
                "DRelative": 0.0,
                "SRelative": 1.0,
                "total": 1,
                "s": 1
            },
            "publicConstructorParameter": {
                "d": 0,
                "DRelative": 0.0,
                "SRelative": 1.0,
                "total": 1,
                "s": 1
            },
            "publicMethodReturn": {
                "d": 1,
                "DRelative": 0.5,
                "SRelative": 0.5,
                "total": 2,
                "s": 1
            },
            "protectedField": {
                "d": 0,
                "DRelative": 0,
                "SRelative": 0,
                "total": 0,
                "s": 0
            },
            "numberOfPrivateConstructors": 0,
            "pureTypeSystemPublicConstructors": {
                "d": 0,
                "DRelative": 0.0,
                "SRelative": 1.0,
                "total": 1,
                "s": 1
            },
            "numberOfProtectedConstructors": 0
        },
        {
            "privateField": {
                "d": 0,
                "DRelative": 0,
                "SRelative": 0,
                "total": 0,
                "s": 0
            },
            "protectedConstructorParameter": {
                "d": 0,
                "DRelative": 0,
                "SRelative": 0,
                "total": 0,
                "s": 0
            },
            "protectedMethodParameter": {
                "d": 0,
                "DRelative": 0,
                "SRelative": 0,
                "total": 0,
                "s": 0
            },
            "privateMethodParameter": {
                "d": 0,
                "DRelative": 0,
                "SRelative": 0,
                "total": 0,
                "s": 0
            },
            "privateConstructorParameter": {
                "d": 0,
                "DRelative": 0,
                "SRelative": 0,
                "total": 0,
                "s": 0
            },
            "pureTypeSystemPrivateMethods": {
                "d": 0,
                "DRelative": 0,
                "SRelative": 0,
                "total": 0,
                "s": 0
            },
            "privateMethodReturn": {
                "d": 0,
                "DRelative": 0,
                "SRelative": 0,
                "total": 0,
                "s": 0
            },
            "location": "/opt/groovonomics/temp/altosz_grass/scripts/ListCompassFrameworks.groovy",
            "localVariable": {
                "d": 0,
                "DRelative": 0,
                "SRelative": 0,
                "total": 0,
                "s": 0
            },
            "pureTypeSystemProtectedConstructors": {
                "d": 0,
                "DRelative": 0,
                "SRelative": 0,
                "total": 0,
                "s": 0
            },
            "isScript": true,
            "publicField": {
                "d": 0,
                "DRelative": 0,
                "SRelative": 0,
                "total": 0,
                "s": 0
            },
            "pureTypeSystemProtectedMethods": {
                "d": 0,
                "DRelative": 0,
                "SRelative": 0,
                "total": 0,
                "s": 0
            },
            "numberOfPublicConstructors": 2,
            "className": "script1378432045230",
            "pureTypeSystemPrivateConstructors": {
                "d": 0,
                "DRelative": 0,
                "SRelative": 0,
                "total": 0,
                "s": 0
            },
            "protectedMethodReturn": {
                "d": 0,
                "DRelative": 0,
                "SRelative": 0,
                "total": 0,
                "s": 0
            },
            "publicMethodParameter": {
                "d": 0,
                "DRelative": 0.0,
                "SRelative": 1.0,
                "total": 1,
                "s": 1
            },
            "pureTypeSystemPublicMethods": {
                "d": 0,
                "DRelative": 0.0,
                "SRelative": 1.0,
                "total": 1,
                "s": 1
            },
            "publicConstructorParameter": {
                "d": 0,
                "DRelative": 0.0,
                "SRelative": 1.0,
                "total": 1,
                "s": 1
            },
            "publicMethodReturn": {
                "d": 1,
                "DRelative": 0.5,
                "SRelative": 0.5,
                "total": 2,
                "s": 1
            },
            "protectedField": {
                "d": 0,
                "DRelative": 0,
                "SRelative": 0,
                "total": 0,
                "s": 0
            },
            "numberOfPrivateConstructors": 0,
            "pureTypeSystemPublicConstructors": {
                "d": 0,
                "DRelative": 0.0,
                "SRelative": 1.0,
                "total": 1,
                "s": 1
            },
            "numberOfProtectedConstructors": 0
        },
        {
            "privateField": {
                "d": 0,
                "DRelative": 0,
                "SRelative": 0,
                "total": 0,
                "s": 0
            },
            "protectedConstructorParameter": {
                "d": 0,
                "DRelative": 0,
                "SRelative": 0,
                "total": 0,
                "s": 0
            },
            "protectedMethodParameter": {
                "d": 0,
                "DRelative": 0,
                "SRelative": 0,
                "total": 0,
                "s": 0
            },
            "privateMethodParameter": {
                "d": 0,
                "DRelative": 0,
                "SRelative": 0,
                "total": 0,
                "s": 0
            },
            "privateConstructorParameter": {
                "d": 0,
                "DRelative": 0,
                "SRelative": 0,
                "total": 0,
                "s": 0
            },
            "pureTypeSystemPrivateMethods": {
                "d": 0,
                "DRelative": 0,
                "SRelative": 0,
                "total": 0,
                "s": 0
            },
            "privateMethodReturn": {
                "d": 0,
                "DRelative": 0,
                "SRelative": 0,
                "total": 0,
                "s": 0
            },
            "location": "/opt/groovonomics/temp/altosz_grass/scripts/_Install.groovy",
            "localVariable": {
                "d": 0,
                "DRelative": 0,
                "SRelative": 0,
                "total": 0,
                "s": 0
            },
            "pureTypeSystemProtectedConstructors": {
                "d": 0,
                "DRelative": 0,
                "SRelative": 0,
                "total": 0,
                "s": 0
            },
            "isScript": true,
            "publicField": {
                "d": 0,
                "DRelative": 0,
                "SRelative": 0,
                "total": 0,
                "s": 0
            },
            "pureTypeSystemProtectedMethods": {
                "d": 0,
                "DRelative": 0,
                "SRelative": 0,
                "total": 0,
                "s": 0
            },
            "numberOfPublicConstructors": 2,
            "className": "script1378432045442",
            "pureTypeSystemPrivateConstructors": {
                "d": 0,
                "DRelative": 0,
                "SRelative": 0,
                "total": 0,
                "s": 0
            },
            "protectedMethodReturn": {
                "d": 0,
                "DRelative": 0,
                "SRelative": 0,
                "total": 0,
                "s": 0
            },
            "publicMethodParameter": {
                "d": 0,
                "DRelative": 0.0,
                "SRelative": 1.0,
                "total": 1,
                "s": 1
            },
            "pureTypeSystemPublicMethods": {
                "d": 0,
                "DRelative": 0.0,
                "SRelative": 1.0,
                "total": 1,
                "s": 1
            },
            "publicConstructorParameter": {
                "d": 0,
                "DRelative": 0.0,
                "SRelative": 1.0,
                "total": 1,
                "s": 1
            },
            "publicMethodReturn": {
                "d": 1,
                "DRelative": 0.5,
                "SRelative": 0.5,
                "total": 2,
                "s": 1
            },
            "protectedField": {
                "d": 0,
                "DRelative": 0,
                "SRelative": 0,
                "total": 0,
                "s": 0
            },
            "numberOfPrivateConstructors": 0,
            "pureTypeSystemPublicConstructors": {
                "d": 0,
                "DRelative": 0.0,
                "SRelative": 1.0,
                "total": 1,
                "s": 1
            },
            "numberOfProtectedConstructors": 0
        },
        {
            "privateField": {
                "d": 0,
                "DRelative": 0,
                "SRelative": 0,
                "total": 0,
                "s": 0
            },
            "protectedConstructorParameter": {
                "d": 0,
                "DRelative": 0,
                "SRelative": 0,
                "total": 0,
                "s": 0
            },
            "protectedMethodParameter": {
                "d": 0,
                "DRelative": 0,
                "SRelative": 0,
                "total": 0,
                "s": 0
            },
            "privateMethodParameter": {
                "d": 0,
                "DRelative": 0,
                "SRelative": 0,
                "total": 0,
                "s": 0
            },
            "privateConstructorParameter": {
                "d": 0,
                "DRelative": 0,
                "SRelative": 0,
                "total": 0,
                "s": 0
            },
            "pureTypeSystemPrivateMethods": {
                "d": 0,
                "DRelative": 0,
                "SRelative": 0,
                "total": 0,
                "s": 0
            },
            "privateMethodReturn": {
                "d": 0,
                "DRelative": 0,
                "SRelative": 0,
                "total": 0,
                "s": 0
            },
            "location": "/opt/groovonomics/temp/altosz_grass/scripts/_Upgrade.groovy",
            "localVariable": {
                "d": 0,
                "DRelative": 0,
                "SRelative": 0,
                "total": 0,
                "s": 0
            },
            "pureTypeSystemProtectedConstructors": {
                "d": 0,
                "DRelative": 0,
                "SRelative": 0,
                "total": 0,
                "s": 0
            },
            "isScript": true,
            "publicField": {
                "d": 0,
                "DRelative": 0,
                "SRelative": 0,
                "total": 0,
                "s": 0
            },
            "pureTypeSystemProtectedMethods": {
                "d": 0,
                "DRelative": 0,
                "SRelative": 0,
                "total": 0,
                "s": 0
            },
            "numberOfPublicConstructors": 2,
            "className": "script1378432046822",
            "pureTypeSystemPrivateConstructors": {
                "d": 0,
                "DRelative": 0,
                "SRelative": 0,
                "total": 0,
                "s": 0
            },
            "protectedMethodReturn": {
                "d": 0,
                "DRelative": 0,
                "SRelative": 0,
                "total": 0,
                "s": 0
            },
            "publicMethodParameter": {
                "d": 0,
                "DRelative": 0.0,
                "SRelative": 1.0,
                "total": 1,
                "s": 1
            },
            "pureTypeSystemPublicMethods": {
                "d": 0,
                "DRelative": 0.0,
                "SRelative": 1.0,
                "total": 1,
                "s": 1
            },
            "publicConstructorParameter": {
                "d": 0,
                "DRelative": 0.0,
                "SRelative": 1.0,
                "total": 1,
                "s": 1
            },
            "publicMethodReturn": {
                "d": 1,
                "DRelative": 0.5,
                "SRelative": 0.5,
                "total": 2,
                "s": 1
            },
            "protectedField": {
                "d": 0,
                "DRelative": 0,
                "SRelative": 0,
                "total": 0,
                "s": 0
            },
            "numberOfPrivateConstructors": 0,
            "pureTypeSystemPublicConstructors": {
                "d": 0,
                "DRelative": 0.0,
                "SRelative": 1.0,
                "total": 1,
                "s": 1
            },
            "numberOfProtectedConstructors": 0
        },
        {
            "privateField": {
                "d": 0,
                "DRelative": 0,
                "SRelative": 0,
                "total": 0,
                "s": 0
            },
            "protectedConstructorParameter": {
                "d": 0,
                "DRelative": 0,
                "SRelative": 0,
                "total": 0,
                "s": 0
            },
            "protectedMethodParameter": {
                "d": 0,
                "DRelative": 0,
                "SRelative": 0,
                "total": 0,
                "s": 0
            },
            "privateMethodParameter": {
                "d": 0,
                "DRelative": 0,
                "SRelative": 0,
                "total": 0,
                "s": 0
            },
            "privateConstructorParameter": {
                "d": 0,
                "DRelative": 0,
                "SRelative": 0,
                "total": 0,
                "s": 0
            },
            "pureTypeSystemPrivateMethods": {
                "d": 0,
                "DRelative": 0,
                "SRelative": 0,
                "total": 0,
                "s": 0
            },
            "privateMethodReturn": {
                "d": 0,
                "DRelative": 0,
                "SRelative": 0,
                "total": 0,
                "s": 0
            },
            "location": "/opt/groovonomics/temp/altosz_grass/scripts/CompassInit.groovy",
            "localVariable": {
                "d": 1,
                "DRelative": 1.0,
                "SRelative": 0.0,
                "total": 1,
                "s": 0
            },
            "pureTypeSystemProtectedConstructors": {
                "d": 0,
                "DRelative": 0,
                "SRelative": 0,
                "total": 0,
                "s": 0
            },
            "isScript": true,
            "publicField": {
                "d": 0,
                "DRelative": 0,
                "SRelative": 0,
                "total": 0,
                "s": 0
            },
            "pureTypeSystemProtectedMethods": {
                "d": 0,
                "DRelative": 0,
                "SRelative": 0,
                "total": 0,
                "s": 0
            },
            "numberOfPublicConstructors": 2,
            "className": "script1378432047809",
            "pureTypeSystemPrivateConstructors": {
                "d": 0,
                "DRelative": 0,
                "SRelative": 0,
                "total": 0,
                "s": 0
            },
            "protectedMethodReturn": {
                "d": 0,
                "DRelative": 0,
                "SRelative": 0,
                "total": 0,
                "s": 0
            },
            "publicMethodParameter": {
                "d": 0,
                "DRelative": 0.0,
                "SRelative": 1.0,
                "total": 1,
                "s": 1
            },
            "pureTypeSystemPublicMethods": {
                "d": 0,
                "DRelative": 0.0,
                "SRelative": 1.0,
                "total": 1,
                "s": 1
            },
            "publicConstructorParameter": {
                "d": 0,
                "DRelative": 0.0,
                "SRelative": 1.0,
                "total": 1,
                "s": 1
            },
            "publicMethodReturn": {
                "d": 1,
                "DRelative": 0.5,
                "SRelative": 0.5,
                "total": 2,
                "s": 1
            },
            "protectedField": {
                "d": 0,
                "DRelative": 0,
                "SRelative": 0,
                "total": 0,
                "s": 0
            },
            "numberOfPrivateConstructors": 0,
            "pureTypeSystemPublicConstructors": {
                "d": 0,
                "DRelative": 0.0,
                "SRelative": 1.0,
                "total": 1,
                "s": 1
            },
            "numberOfProtectedConstructors": 0
        },
        {
            "privateField": {
                "d": 0,
                "DRelative": 0,
                "SRelative": 0,
                "total": 0,
                "s": 0
            },
            "protectedConstructorParameter": {
                "d": 0,
                "DRelative": 0,
                "SRelative": 0,
                "total": 0,
                "s": 0
            },
            "protectedMethodParameter": {
                "d": 0,
                "DRelative": 0,
                "SRelative": 0,
                "total": 0,
                "s": 0
            },
            "privateMethodParameter": {
                "d": 0,
                "DRelative": 0,
                "SRelative": 0,
                "total": 0,
                "s": 0
            },
            "privateConstructorParameter": {
                "d": 0,
                "DRelative": 0,
                "SRelative": 0,
                "total": 0,
                "s": 0
            },
            "pureTypeSystemPrivateMethods": {
                "d": 0,
                "DRelative": 0,
                "SRelative": 0,
                "total": 0,
                "s": 0
            },
            "privateMethodReturn": {
                "d": 0,
                "DRelative": 0,
                "SRelative": 0,
                "total": 0,
                "s": 0
            },
            "location": "/opt/groovonomics/temp/altosz_grass/scripts/GridImg.groovy",
            "localVariable": {
                "d": 1,
                "DRelative": 0.25,
                "SRelative": 0.75,
                "total": 4,
                "s": 3
            },
            "pureTypeSystemProtectedConstructors": {
                "d": 0,
                "DRelative": 0,
                "SRelative": 0,
                "total": 0,
                "s": 0
            },
            "isScript": true,
            "publicField": {
                "d": 0,
                "DRelative": 0,
                "SRelative": 0,
                "total": 0,
                "s": 0
            },
            "pureTypeSystemProtectedMethods": {
                "d": 0,
                "DRelative": 0,
                "SRelative": 0,
                "total": 0,
                "s": 0
            },
            "numberOfPublicConstructors": 2,
            "className": "script1378432052027",
            "pureTypeSystemPrivateConstructors": {
                "d": 0,
                "DRelative": 0,
                "SRelative": 0,
                "total": 0,
                "s": 0
            },
            "protectedMethodReturn": {
                "d": 0,
                "DRelative": 0,
                "SRelative": 0,
                "total": 0,
                "s": 0
            },
            "publicMethodParameter": {
                "d": 0,
                "DRelative": 0.0,
                "SRelative": 1.0,
                "total": 1,
                "s": 1
            },
            "pureTypeSystemPublicMethods": {
                "d": 0,
                "DRelative": 0.0,
                "SRelative": 1.0,
                "total": 1,
                "s": 1
            },
            "publicConstructorParameter": {
                "d": 0,
                "DRelative": 0.0,
                "SRelative": 1.0,
                "total": 1,
                "s": 1
            },
            "publicMethodReturn": {
                "d": 1,
                "DRelative": 0.5,
                "SRelative": 0.5,
                "total": 2,
                "s": 1
            },
            "protectedField": {
                "d": 0,
                "DRelative": 0,
                "SRelative": 0,
                "total": 0,
                "s": 0
            },
            "numberOfPrivateConstructors": 0,
            "pureTypeSystemPublicConstructors": {
                "d": 0,
                "DRelative": 0.0,
                "SRelative": 1.0,
                "total": 1,
                "s": 1
            },
            "numberOfProtectedConstructors": 0
        },
        {
            "privateField": {
                "d": 0,
                "DRelative": 0,
                "SRelative": 0,
                "total": 0,
                "s": 0
            },
            "protectedConstructorParameter": {
                "d": 0,
                "DRelative": 0,
                "SRelative": 0,
                "total": 0,
                "s": 0
            },
            "protectedMethodParameter": {
                "d": 0,
                "DRelative": 0,
                "SRelative": 0,
                "total": 0,
                "s": 0
            },
            "privateMethodParameter": {
                "d": 0,
                "DRelative": 0,
                "SRelative": 0,
                "total": 0,
                "s": 0
            },
            "privateConstructorParameter": {
                "d": 0,
                "DRelative": 0,
                "SRelative": 0,
                "total": 0,
                "s": 0
            },
            "pureTypeSystemPrivateMethods": {
                "d": 0,
                "DRelative": 0,
                "SRelative": 0,
                "total": 0,
                "s": 0
            },
            "privateMethodReturn": {
                "d": 0,
                "DRelative": 0,
                "SRelative": 0,
                "total": 0,
                "s": 0
            },
            "location": "/opt/groovonomics/temp/altosz_grass/scripts/CompileCss.groovy",
            "localVariable": {
                "d": 1,
                "DRelative": 0.25,
                "SRelative": 0.75,
                "total": 4,
                "s": 3
            },
            "pureTypeSystemProtectedConstructors": {
                "d": 0,
                "DRelative": 0,
                "SRelative": 0,
                "total": 0,
                "s": 0
            },
            "isScript": true,
            "publicField": {
                "d": 0,
                "DRelative": 0,
                "SRelative": 0,
                "total": 0,
                "s": 0
            },
            "pureTypeSystemProtectedMethods": {
                "d": 0,
                "DRelative": 0,
                "SRelative": 0,
                "total": 0,
                "s": 0
            },
            "numberOfPublicConstructors": 2,
            "className": "script1378432056044",
            "pureTypeSystemPrivateConstructors": {
                "d": 0,
                "DRelative": 0,
                "SRelative": 0,
                "total": 0,
                "s": 0
            },
            "protectedMethodReturn": {
                "d": 0,
                "DRelative": 0,
                "SRelative": 0,
                "total": 0,
                "s": 0
            },
            "publicMethodParameter": {
                "d": 0,
                "DRelative": 0.0,
                "SRelative": 1.0,
                "total": 1,
                "s": 1
            },
            "pureTypeSystemPublicMethods": {
                "d": 0,
                "DRelative": 0.0,
                "SRelative": 1.0,
                "total": 1,
                "s": 1
            },
            "publicConstructorParameter": {
                "d": 0,
                "DRelative": 0.0,
                "SRelative": 1.0,
                "total": 1,
                "s": 1
            },
            "publicMethodReturn": {
                "d": 1,
                "DRelative": 0.5,
                "SRelative": 0.5,
                "total": 2,
                "s": 1
            },
            "protectedField": {
                "d": 0,
                "DRelative": 0,
                "SRelative": 0,
                "total": 0,
                "s": 0
            },
            "numberOfPrivateConstructors": 0,
            "pureTypeSystemPublicConstructors": {
                "d": 0,
                "DRelative": 0.0,
                "SRelative": 1.0,
                "total": 1,
                "s": 1
            },
            "numberOfProtectedConstructors": 0
        },
        {
            "privateField": {
                "d": 0,
                "DRelative": 0,
                "SRelative": 0,
                "total": 0,
                "s": 0
            },
            "protectedConstructorParameter": {
                "d": 0,
                "DRelative": 0,
                "SRelative": 0,
                "total": 0,
                "s": 0
            },
            "protectedMethodParameter": {
                "d": 0,
                "DRelative": 0,
                "SRelative": 0,
                "total": 0,
                "s": 0
            },
            "privateMethodParameter": {
                "d": 0,
                "DRelative": 0,
                "SRelative": 0,
                "total": 0,
                "s": 0
            },
            "privateConstructorParameter": {
                "d": 0,
                "DRelative": 0,
                "SRelative": 0,
                "total": 0,
                "s": 0
            },
            "pureTypeSystemPrivateMethods": {
                "d": 0,
                "DRelative": 0,
                "SRelative": 0,
                "total": 0,
                "s": 0
            },
            "privateMethodReturn": {
                "d": 0,
                "DRelative": 0,
                "SRelative": 0,
                "total": 0,
                "s": 0
            },
            "location": "/opt/groovonomics/temp/altosz_grass/scripts/_Uninstall.groovy",
            "localVariable": {
                "d": 0,
                "DRelative": 0,
                "SRelative": 0,
                "total": 0,
                "s": 0
            },
            "pureTypeSystemProtectedConstructors": {
                "d": 0,
                "DRelative": 0,
                "SRelative": 0,
                "total": 0,
                "s": 0
            },
            "isScript": true,
            "publicField": {
                "d": 0,
                "DRelative": 0,
                "SRelative": 0,
                "total": 0,
                "s": 0
            },
            "pureTypeSystemProtectedMethods": {
                "d": 0,
                "DRelative": 0,
                "SRelative": 0,
                "total": 0,
                "s": 0
            },
            "numberOfPublicConstructors": 2,
            "className": "script1378432057037",
            "pureTypeSystemPrivateConstructors": {
                "d": 0,
                "DRelative": 0,
                "SRelative": 0,
                "total": 0,
                "s": 0
            },
            "protectedMethodReturn": {
                "d": 0,
                "DRelative": 0,
                "SRelative": 0,
                "total": 0,
                "s": 0
            },
            "publicMethodParameter": {
                "d": 0,
                "DRelative": 0.0,
                "SRelative": 1.0,
                "total": 1,
                "s": 1
            },
            "pureTypeSystemPublicMethods": {
                "d": 0,
                "DRelative": 0.0,
                "SRelative": 1.0,
                "total": 1,
                "s": 1
            },
            "publicConstructorParameter": {
                "d": 0,
                "DRelative": 0.0,
                "SRelative": 1.0,
                "total": 1,
                "s": 1
            },
            "publicMethodReturn": {
                "d": 1,
                "DRelative": 0.5,
                "SRelative": 0.5,
                "total": 2,
                "s": 1
            },
            "protectedField": {
                "d": 0,
                "DRelative": 0,
                "SRelative": 0,
                "total": 0,
                "s": 0
            },
            "numberOfPrivateConstructors": 0,
            "pureTypeSystemPublicConstructors": {
                "d": 0,
                "DRelative": 0.0,
                "SRelative": 1.0,
                "total": 1,
                "s": 1
            },
            "numberOfProtectedConstructors": 0
        },
        {
            "privateField": {
                "d": 0,
                "DRelative": 0,
                "SRelative": 0,
                "total": 0,
                "s": 0
            },
            "protectedConstructorParameter": {
                "d": 0,
                "DRelative": 0,
                "SRelative": 0,
                "total": 0,
                "s": 0
            },
            "protectedMethodParameter": {
                "d": 0,
                "DRelative": 0,
                "SRelative": 0,
                "total": 0,
                "s": 0
            },
            "privateMethodParameter": {
                "d": 0,
                "DRelative": 0,
                "SRelative": 0,
                "total": 0,
                "s": 0
            },
            "privateConstructorParameter": {
                "d": 0,
                "DRelative": 0,
                "SRelative": 0,
                "total": 0,
                "s": 0
            },
            "pureTypeSystemPrivateMethods": {
                "d": 0,
                "DRelative": 0,
                "SRelative": 0,
                "total": 0,
                "s": 0
            },
            "privateMethodReturn": {
                "d": 0,
                "DRelative": 0,
                "SRelative": 0,
                "total": 0,
                "s": 0
            },
            "location": "/opt/groovonomics/temp/altosz_grass/scripts/_Compass.groovy",
            "localVariable": {
                "d": 0,
                "DRelative": 0,
                "SRelative": 0,
                "total": 0,
                "s": 0
            },
            "pureTypeSystemProtectedConstructors": {
                "d": 0,
                "DRelative": 0,
                "SRelative": 0,
                "total": 0,
                "s": 0
            },
            "isScript": true,
            "publicField": {
                "d": 0,
                "DRelative": 0,
                "SRelative": 0,
                "total": 0,
                "s": 0
            },
            "pureTypeSystemProtectedMethods": {
                "d": 0,
                "DRelative": 0,
                "SRelative": 0,
                "total": 0,
                "s": 0
            },
            "numberOfPublicConstructors": 2,
            "className": "script1378432059836",
            "pureTypeSystemPrivateConstructors": {
                "d": 0,
                "DRelative": 0,
                "SRelative": 0,
                "total": 0,
                "s": 0
            },
            "protectedMethodReturn": {
                "d": 0,
                "DRelative": 0,
                "SRelative": 0,
                "total": 0,
                "s": 0
            },
            "publicMethodParameter": {
                "d": 0,
                "DRelative": 0.0,
                "SRelative": 1.0,
                "total": 1,
                "s": 1
            },
            "pureTypeSystemPublicMethods": {
                "d": 0,
                "DRelative": 0.0,
                "SRelative": 1.0,
                "total": 1,
                "s": 1
            },
            "publicConstructorParameter": {
                "d": 0,
                "DRelative": 0.0,
                "SRelative": 1.0,
                "total": 1,
                "s": 1
            },
            "publicMethodReturn": {
                "d": 1,
                "DRelative": 0.5,
                "SRelative": 0.5,
                "total": 2,
                "s": 1
            },
            "protectedField": {
                "d": 0,
                "DRelative": 0,
                "SRelative": 0,
                "total": 0,
                "s": 0
            },
            "numberOfPrivateConstructors": 0,
            "pureTypeSystemPublicConstructors": {
                "d": 0,
                "DRelative": 0.0,
                "SRelative": 1.0,
                "total": 1,
                "s": 1
            },
            "numberOfProtectedConstructors": 0
        },
        {
            "privateField": {
                "d": 0,
                "DRelative": 0,
                "SRelative": 0,
                "total": 0,
                "s": 0
            },
            "protectedConstructorParameter": {
                "d": 0,
                "DRelative": 0,
                "SRelative": 0,
                "total": 0,
                "s": 0
            },
            "protectedMethodParameter": {
                "d": 0,
                "DRelative": 0,
                "SRelative": 0,
                "total": 0,
                "s": 0
            },
            "privateMethodParameter": {
                "d": 0,
                "DRelative": 0,
                "SRelative": 0,
                "total": 0,
                "s": 0
            },
            "privateConstructorParameter": {
                "d": 0,
                "DRelative": 0,
                "SRelative": 0,
                "total": 0,
                "s": 0
            },
            "pureTypeSystemPrivateMethods": {
                "d": 0,
                "DRelative": 0,
                "SRelative": 0,
                "total": 0,
                "s": 0
            },
            "privateMethodReturn": {
                "d": 0,
                "DRelative": 0,
                "SRelative": 0,
                "total": 0,
                "s": 0
            },
            "location": "/opt/groovonomics/temp/altosz_grass/scripts/_CompassFrameworks.groovy",
            "localVariable": {
                "d": 0,
                "DRelative": 0,
                "SRelative": 0,
                "total": 0,
                "s": 0
            },
            "pureTypeSystemProtectedConstructors": {
                "d": 0,
                "DRelative": 0,
                "SRelative": 0,
                "total": 0,
                "s": 0
            },
            "isScript": true,
            "publicField": {
                "d": 0,
                "DRelative": 0,
                "SRelative": 0,
                "total": 0,
                "s": 0
            },
            "pureTypeSystemProtectedMethods": {
                "d": 0,
                "DRelative": 0,
                "SRelative": 0,
                "total": 0,
                "s": 0
            },
            "numberOfPublicConstructors": 2,
            "className": "script1378432062234",
            "pureTypeSystemPrivateConstructors": {
                "d": 0,
                "DRelative": 0,
                "SRelative": 0,
                "total": 0,
                "s": 0
            },
            "protectedMethodReturn": {
                "d": 0,
                "DRelative": 0,
                "SRelative": 0,
                "total": 0,
                "s": 0
            },
            "publicMethodParameter": {
                "d": 0,
                "DRelative": 0.0,
                "SRelative": 1.0,
                "total": 1,
                "s": 1
            },
            "pureTypeSystemPublicMethods": {
                "d": 0,
                "DRelative": 0.0,
                "SRelative": 1.0,
                "total": 1,
                "s": 1
            },
            "publicConstructorParameter": {
                "d": 0,
                "DRelative": 0.0,
                "SRelative": 1.0,
                "total": 1,
                "s": 1
            },
            "publicMethodReturn": {
                "d": 1,
                "DRelative": 0.5,
                "SRelative": 0.5,
                "total": 2,
                "s": 1
            },
            "protectedField": {
                "d": 0,
                "DRelative": 0,
                "SRelative": 0,
                "total": 0,
                "s": 0
            },
            "numberOfPrivateConstructors": 0,
            "pureTypeSystemPublicConstructors": {
                "d": 0,
                "DRelative": 0.0,
                "SRelative": 1.0,
                "total": 1,
                "s": 1
            },
            "numberOfProtectedConstructors": 0
        }
    ],
    "name": ""
}