{
    "id": "Jdourd_CodeStory-grails",
    "classes": [
        {
            "privateField": {
                "d": 0,
                "DRelative": 0,
                "SRelative": 0,
                "total": 0,
                "s": 0
            },
            "protectedConstructorParameter": {
                "d": 0,
                "DRelative": 0,
                "SRelative": 0,
                "total": 0,
                "s": 0
            },
            "protectedMethodParameter": {
                "d": 0,
                "DRelative": 0,
                "SRelative": 0,
                "total": 0,
                "s": 0
            },
            "privateMethodParameter": {
                "d": 0,
                "DRelative": 0,
                "SRelative": 0,
                "total": 0,
                "s": 0
            },
            "privateConstructorParameter": {
                "d": 0,
                "DRelative": 0,
                "SRelative": 0,
                "total": 0,
                "s": 0
            },
            "pureTypeSystemPrivateMethods": {
                "d": 0,
                "DRelative": 0,
                "SRelative": 0,
                "total": 0,
                "s": 0
            },
            "privateMethodReturn": {
                "d": 0,
                "DRelative": 0,
                "SRelative": 0,
                "total": 0,
                "s": 0
            },
            "location": "/opt/groovonomics/temp/Jdourd_CodeStory-grails/test/unit/grails/story/SolveEquationControllerTests.groovy",
            "localVariable": {
                "d": 0,
                "DRelative": 0,
                "SRelative": 0,
                "total": 0,
                "s": 0
            },
            "pureTypeSystemProtectedConstructors": {
                "d": 0,
                "DRelative": 0,
                "SRelative": 0,
                "total": 0,
                "s": 0
            },
            "isScript": false,
            "publicField": {
                "d": 0,
                "DRelative": 0,
                "SRelative": 0,
                "total": 0,
                "s": 0
            },
            "pureTypeSystemProtectedMethods": {
                "d": 0,
                "DRelative": 0,
                "SRelative": 0,
                "total": 0,
                "s": 0
            },
            "numberOfPublicConstructors": 0,
            "className": "grails.story.SolveEquationControllerTests",
            "pureTypeSystemPrivateConstructors": {
                "d": 0,
                "DRelative": 0,
                "SRelative": 0,
                "total": 0,
                "s": 0
            },
            "protectedMethodReturn": {
                "d": 0,
                "DRelative": 0,
                "SRelative": 0,
                "total": 0,
                "s": 0
            },
            "publicMethodParameter": {
                "d": 2,
                "DRelative": 1.0,
                "SRelative": 0.0,
                "total": 2,
                "s": 0
            },
            "pureTypeSystemPublicMethods": {
                "d": 1,
                "DRelative": 1.0,
                "SRelative": 0.0,
                "total": 1,
                "s": 0
            },
            "publicConstructorParameter": {
                "d": 0,
                "DRelative": 0,
                "SRelative": 0,
                "total": 0,
                "s": 0
            },
            "publicMethodReturn": {
                "d": 1,
                "DRelative": 0.2,
                "SRelative": 0.8,
                "total": 5,
                "s": 4
            },
            "protectedField": {
                "d": 0,
                "DRelative": 0,
                "SRelative": 0,
                "total": 0,
                "s": 0
            },
            "numberOfPrivateConstructors": 0,
            "pureTypeSystemPublicConstructors": {
                "d": 0,
                "DRelative": 0,
                "SRelative": 0,
                "total": 0,
                "s": 0
            },
            "numberOfProtectedConstructors": 0
        },
        {
            "privateField": {
                "d": 0,
                "DRelative": 0,
                "SRelative": 0,
                "total": 0,
                "s": 0
            },
            "protectedConstructorParameter": {
                "d": 0,
                "DRelative": 0,
                "SRelative": 0,
                "total": 0,
                "s": 0
            },
            "protectedMethodParameter": {
                "d": 0,
                "DRelative": 0,
                "SRelative": 0,
                "total": 0,
                "s": 0
            },
            "privateMethodParameter": {
                "d": 0,
                "DRelative": 0,
                "SRelative": 0,
                "total": 0,
                "s": 0
            },
            "privateConstructorParameter": {
                "d": 0,
                "DRelative": 0,
                "SRelative": 0,
                "total": 0,
                "s": 0
            },
            "pureTypeSystemPrivateMethods": {
                "d": 0,
                "DRelative": 0,
                "SRelative": 0,
                "total": 0,
                "s": 0
            },
            "privateMethodReturn": {
                "d": 0,
                "DRelative": 0,
                "SRelative": 0,
                "total": 0,
                "s": 0
            },
            "location": "/opt/groovonomics/temp/Jdourd_CodeStory-grails/test/unit/grails/story/TripSolverServiceTests.groovy",
            "localVariable": {
                "d": 14,
                "DRelative": 1.0,
                "SRelative": 0.0,
                "total": 14,
                "s": 0
            },
            "pureTypeSystemProtectedConstructors": {
                "d": 0,
                "DRelative": 0,
                "SRelative": 0,
                "total": 0,
                "s": 0
            },
            "isScript": false,
            "publicField": {
                "d": 0,
                "DRelative": 0,
                "SRelative": 0,
                "total": 0,
                "s": 0
            },
            "pureTypeSystemProtectedMethods": {
                "d": 0,
                "DRelative": 0,
                "SRelative": 0,
                "total": 0,
                "s": 0
            },
            "numberOfPublicConstructors": 0,
            "className": "grails.story.TripSolverServiceTests",
            "pureTypeSystemPrivateConstructors": {
                "d": 0,
                "DRelative": 0,
                "SRelative": 0,
                "total": 0,
                "s": 0
            },
            "protectedMethodReturn": {
                "d": 0,
                "DRelative": 0,
                "SRelative": 0,
                "total": 0,
                "s": 0
            },
            "publicMethodParameter": {
                "d": 0,
                "DRelative": 0,
                "SRelative": 0,
                "total": 0,
                "s": 0
            },
            "pureTypeSystemPublicMethods": {
                "d": 0,
                "DRelative": 0,
                "SRelative": 0,
                "total": 0,
                "s": 0
            },
            "publicConstructorParameter": {
                "d": 0,
                "DRelative": 0,
                "SRelative": 0,
                "total": 0,
                "s": 0
            },
            "publicMethodReturn": {
                "d": 0,
                "DRelative": 0.0,
                "SRelative": 1.0,
                "total": 7,
                "s": 7
            },
            "protectedField": {
                "d": 0,
                "DRelative": 0,
                "SRelative": 0,
                "total": 0,
                "s": 0
            },
            "numberOfPrivateConstructors": 0,
            "pureTypeSystemPublicConstructors": {
                "d": 0,
                "DRelative": 0,
                "SRelative": 0,
                "total": 0,
                "s": 0
            },
            "numberOfProtectedConstructors": 0
        },
        {
            "privateField": {
                "d": 0,
                "DRelative": 0,
                "SRelative": 0,
                "total": 0,
                "s": 0
            },
            "protectedConstructorParameter": {
                "d": 0,
                "DRelative": 0,
                "SRelative": 0,
                "total": 0,
                "s": 0
            },
            "protectedMethodParameter": {
                "d": 0,
                "DRelative": 0,
                "SRelative": 0,
                "total": 0,
                "s": 0
            },
            "privateMethodParameter": {
                "d": 0,
                "DRelative": 0,
                "SRelative": 0,
                "total": 0,
                "s": 0
            },
            "privateConstructorParameter": {
                "d": 0,
                "DRelative": 0,
                "SRelative": 0,
                "total": 0,
                "s": 0
            },
            "pureTypeSystemPrivateMethods": {
                "d": 0,
                "DRelative": 0,
                "SRelative": 0,
                "total": 0,
                "s": 0
            },
            "privateMethodReturn": {
                "d": 0,
                "DRelative": 0,
                "SRelative": 0,
                "total": 0,
                "s": 0
            },
            "location": "/opt/groovonomics/temp/Jdourd_CodeStory-grails/test/unit/grails/story/JajascriptControllerTests.groovy",
            "localVariable": {
                "d": 5,
                "DRelative": 1.0,
                "SRelative": 0.0,
                "total": 5,
                "s": 0
            },
            "pureTypeSystemProtectedConstructors": {
                "d": 0,
                "DRelative": 0,
                "SRelative": 0,
                "total": 0,
                "s": 0
            },
            "isScript": false,
            "publicField": {
                "d": 0,
                "DRelative": 0,
                "SRelative": 0,
                "total": 0,
                "s": 0
            },
            "pureTypeSystemProtectedMethods": {
                "d": 0,
                "DRelative": 0,
                "SRelative": 0,
                "total": 0,
                "s": 0
            },
            "numberOfPublicConstructors": 0,
            "className": "grails.story.JajascriptControllerTests",
            "pureTypeSystemPrivateConstructors": {
                "d": 0,
                "DRelative": 0,
                "SRelative": 0,
                "total": 0,
                "s": 0
            },
            "protectedMethodReturn": {
                "d": 0,
                "DRelative": 0,
                "SRelative": 0,
                "total": 0,
                "s": 0
            },
            "publicMethodParameter": {
                "d": 2,
                "DRelative": 1.0,
                "SRelative": 0.0,
                "total": 2,
                "s": 0
            },
            "pureTypeSystemPublicMethods": {
                "d": 1,
                "DRelative": 1.0,
                "SRelative": 0.0,
                "total": 1,
                "s": 0
            },
            "publicConstructorParameter": {
                "d": 0,
                "DRelative": 0,
                "SRelative": 0,
                "total": 0,
                "s": 0
            },
            "publicMethodReturn": {
                "d": 1,
                "DRelative": 0.3333333333333333,
                "SRelative": 0.6666666666666666,
                "total": 3,
                "s": 2
            },
            "protectedField": {
                "d": 0,
                "DRelative": 0,
                "SRelative": 0,
                "total": 0,
                "s": 0
            },
            "numberOfPrivateConstructors": 0,
            "pureTypeSystemPublicConstructors": {
                "d": 0,
                "DRelative": 0,
                "SRelative": 0,
                "total": 0,
                "s": 0
            },
            "numberOfProtectedConstructors": 0
        },
        {
            "privateField": {
                "d": 0,
                "DRelative": 0,
                "SRelative": 0,
                "total": 0,
                "s": 0
            },
            "protectedConstructorParameter": {
                "d": 0,
                "DRelative": 0,
                "SRelative": 0,
                "total": 0,
                "s": 0
            },
            "protectedMethodParameter": {
                "d": 0,
                "DRelative": 0,
                "SRelative": 0,
                "total": 0,
                "s": 0
            },
            "privateMethodParameter": {
                "d": 0,
                "DRelative": 0,
                "SRelative": 0,
                "total": 0,
                "s": 0
            },
            "privateConstructorParameter": {
                "d": 0,
                "DRelative": 0,
                "SRelative": 0,
                "total": 0,
                "s": 0
            },
            "pureTypeSystemPrivateMethods": {
                "d": 0,
                "DRelative": 0,
                "SRelative": 0,
                "total": 0,
                "s": 0
            },
            "privateMethodReturn": {
                "d": 0,
                "DRelative": 0,
                "SRelative": 0,
                "total": 0,
                "s": 0
            },
            "location": "/opt/groovonomics/temp/Jdourd_CodeStory-grails/test/unit/grails/story/ScalaskelControllerTests.groovy",
            "localVariable": {
                "d": 1,
                "DRelative": 1.0,
                "SRelative": 0.0,
                "total": 1,
                "s": 0
            },
            "pureTypeSystemProtectedConstructors": {
                "d": 0,
                "DRelative": 0,
                "SRelative": 0,
                "total": 0,
                "s": 0
            },
            "isScript": false,
            "publicField": {
                "d": 0,
                "DRelative": 0,
                "SRelative": 0,
                "total": 0,
                "s": 0
            },
            "pureTypeSystemProtectedMethods": {
                "d": 0,
                "DRelative": 0,
                "SRelative": 0,
                "total": 0,
                "s": 0
            },
            "numberOfPublicConstructors": 0,
            "className": "grails.story.ScalaskelControllerTests",
            "pureTypeSystemPrivateConstructors": {
                "d": 0,
                "DRelative": 0,
                "SRelative": 0,
                "total": 0,
                "s": 0
            },
            "protectedMethodReturn": {
                "d": 0,
                "DRelative": 0,
                "SRelative": 0,
                "total": 0,
                "s": 0
            },
            "publicMethodParameter": {
                "d": 2,
                "DRelative": 1.0,
                "SRelative": 0.0,
                "total": 2,
                "s": 0
            },
            "pureTypeSystemPublicMethods": {
                "d": 1,
                "DRelative": 1.0,
                "SRelative": 0.0,
                "total": 1,
                "s": 0
            },
            "publicConstructorParameter": {
                "d": 0,
                "DRelative": 0,
                "SRelative": 0,
                "total": 0,
                "s": 0
            },
            "publicMethodReturn": {
                "d": 1,
                "DRelative": 0.09090909090909091,
                "SRelative": 0.9090909090909091,
                "total": 11,
                "s": 10
            },
            "protectedField": {
                "d": 0,
                "DRelative": 0,
                "SRelative": 0,
                "total": 0,
                "s": 0
            },
            "numberOfPrivateConstructors": 0,
            "pureTypeSystemPublicConstructors": {
                "d": 0,
                "DRelative": 0,
                "SRelative": 0,
                "total": 0,
                "s": 0
            },
            "numberOfProtectedConstructors": 0
        },
        {
            "privateField": {
                "d": 0,
                "DRelative": 0,
                "SRelative": 0,
                "total": 0,
                "s": 0
            },
            "protectedConstructorParameter": {
                "d": 0,
                "DRelative": 0,
                "SRelative": 0,
                "total": 0,
                "s": 0
            },
            "protectedMethodParameter": {
                "d": 0,
                "DRelative": 0,
                "SRelative": 0,
                "total": 0,
                "s": 0
            },
            "privateMethodParameter": {
                "d": 0,
                "DRelative": 0,
                "SRelative": 0,
                "total": 0,
                "s": 0
            },
            "privateConstructorParameter": {
                "d": 0,
                "DRelative": 0,
                "SRelative": 0,
                "total": 0,
                "s": 0
            },
            "pureTypeSystemPrivateMethods": {
                "d": 0,
                "DRelative": 0,
                "SRelative": 0,
                "total": 0,
                "s": 0
            },
            "privateMethodReturn": {
                "d": 0,
                "DRelative": 0,
                "SRelative": 0,
                "total": 0,
                "s": 0
            },
            "location": "/opt/groovonomics/temp/Jdourd_CodeStory-grails/test/unit/grails/story/TripSolverServicePerformanceTests.groovy",
            "localVariable": {
                "d": 4,
                "DRelative": 0.4444444444444444,
                "SRelative": 0.5555555555555556,
                "total": 9,
                "s": 5
            },
            "pureTypeSystemProtectedConstructors": {
                "d": 0,
                "DRelative": 0,
                "SRelative": 0,
                "total": 0,
                "s": 0
            },
            "isScript": false,
            "publicField": {
                "d": 0,
                "DRelative": 0,
                "SRelative": 0,
                "total": 0,
                "s": 0
            },
            "pureTypeSystemProtectedMethods": {
                "d": 0,
                "DRelative": 0,
                "SRelative": 0,
                "total": 0,
                "s": 0
            },
            "numberOfPublicConstructors": 0,
            "className": "grails.story.TripSolverServicePerformanceTests",
            "pureTypeSystemPrivateConstructors": {
                "d": 0,
                "DRelative": 0,
                "SRelative": 0,
                "total": 0,
                "s": 0
            },
            "protectedMethodReturn": {
                "d": 0,
                "DRelative": 0,
                "SRelative": 0,
                "total": 0,
                "s": 0
            },
            "publicMethodParameter": {
                "d": 0,
                "DRelative": 0,
                "SRelative": 0,
                "total": 0,
                "s": 0
            },
            "pureTypeSystemPublicMethods": {
                "d": 0,
                "DRelative": 0,
                "SRelative": 0,
                "total": 0,
                "s": 0
            },
            "publicConstructorParameter": {
                "d": 0,
                "DRelative": 0,
                "SRelative": 0,
                "total": 0,
                "s": 0
            },
            "publicMethodReturn": {
                "d": 0,
                "DRelative": 0.0,
                "SRelative": 1.0,
                "total": 1,
                "s": 1
            },
            "protectedField": {
                "d": 0,
                "DRelative": 0,
                "SRelative": 0,
                "total": 0,
                "s": 0
            },
            "numberOfPrivateConstructors": 0,
            "pureTypeSystemPublicConstructors": {
                "d": 0,
                "DRelative": 0,
                "SRelative": 0,
                "total": 0,
                "s": 0
            },
            "numberOfProtectedConstructors": 0
        },
        {
            "privateField": {
                "d": 0,
                "DRelative": 0,
                "SRelative": 0,
                "total": 0,
                "s": 0
            },
            "protectedConstructorParameter": {
                "d": 0,
                "DRelative": 0,
                "SRelative": 0,
                "total": 0,
                "s": 0
            },
            "protectedMethodParameter": {
                "d": 0,
                "DRelative": 0,
                "SRelative": 0,
                "total": 0,
                "s": 0
            },
            "privateMethodParameter": {
                "d": 0,
                "DRelative": 0,
                "SRelative": 0,
                "total": 0,
                "s": 0
            },
            "privateConstructorParameter": {
                "d": 0,
                "DRelative": 0,
                "SRelative": 0,
                "total": 0,
                "s": 0
            },
            "pureTypeSystemPrivateMethods": {
                "d": 0,
                "DRelative": 0,
                "SRelative": 0,
                "total": 0,
                "s": 0
            },
            "privateMethodReturn": {
                "d": 0,
                "DRelative": 0,
                "SRelative": 0,
                "total": 0,
                "s": 0
            },
            "location": "/opt/groovonomics/temp/Jdourd_CodeStory-grails/test/unit/grails/story/SimpleLoggingFiltersTests.groovy",
            "localVariable": {
                "d": 0,
                "DRelative": 0,
                "SRelative": 0,
                "total": 0,
                "s": 0
            },
            "pureTypeSystemProtectedConstructors": {
                "d": 0,
                "DRelative": 0,
                "SRelative": 0,
                "total": 0,
                "s": 0
            },
            "isScript": false,
            "publicField": {
                "d": 0,
                "DRelative": 0,
                "SRelative": 0,
                "total": 0,
                "s": 0
            },
            "pureTypeSystemProtectedMethods": {
                "d": 0,
                "DRelative": 0,
                "SRelative": 0,
                "total": 0,
                "s": 0
            },
            "numberOfPublicConstructors": 0,
            "className": "grails.story.SimpleLoggingFiltersTests",
            "pureTypeSystemPrivateConstructors": {
                "d": 0,
                "DRelative": 0,
                "SRelative": 0,
                "total": 0,
                "s": 0
            },
            "protectedMethodReturn": {
                "d": 0,
                "DRelative": 0,
                "SRelative": 0,
                "total": 0,
                "s": 0
            },
            "publicMethodParameter": {
                "d": 0,
                "DRelative": 0,
                "SRelative": 0,
                "total": 0,
                "s": 0
            },
            "pureTypeSystemPublicMethods": {
                "d": 0,
                "DRelative": 0,
                "SRelative": 0,
                "total": 0,
                "s": 0
            },
            "publicConstructorParameter": {
                "d": 0,
                "DRelative": 0,
                "SRelative": 0,
                "total": 0,
                "s": 0
            },
            "publicMethodReturn": {
                "d": 0,
                "DRelative": 0.0,
                "SRelative": 1.0,
                "total": 1,
                "s": 1
            },
            "protectedField": {
                "d": 0,
                "DRelative": 0,
                "SRelative": 0,
                "total": 0,
                "s": 0
            },
            "numberOfPrivateConstructors": 0,
            "pureTypeSystemPublicConstructors": {
                "d": 0,
                "DRelative": 0,
                "SRelative": 0,
                "total": 0,
                "s": 0
            },
            "numberOfProtectedConstructors": 0
        },
        {
            "privateField": {
                "d": 0,
                "DRelative": 0,
                "SRelative": 0,
                "total": 0,
                "s": 0
            },
            "protectedConstructorParameter": {
                "d": 0,
                "DRelative": 0,
                "SRelative": 0,
                "total": 0,
                "s": 0
            },
            "protectedMethodParameter": {
                "d": 0,
                "DRelative": 0,
                "SRelative": 0,
                "total": 0,
                "s": 0
            },
            "privateMethodParameter": {
                "d": 0,
                "DRelative": 0,
                "SRelative": 0,
                "total": 0,
                "s": 0
            },
            "privateConstructorParameter": {
                "d": 0,
                "DRelative": 0,
                "SRelative": 0,
                "total": 0,
                "s": 0
            },
            "pureTypeSystemPrivateMethods": {
                "d": 0,
                "DRelative": 0,
                "SRelative": 0,
                "total": 0,
                "s": 0
            },
            "privateMethodReturn": {
                "d": 0,
                "DRelative": 0,
                "SRelative": 0,
                "total": 0,
                "s": 0
            },
            "location": "/opt/groovonomics/temp/Jdourd_CodeStory-grails/test/unit/grails/story/HelloControllerTests.groovy",
            "localVariable": {
                "d": 0,
                "DRelative": 0,
                "SRelative": 0,
                "total": 0,
                "s": 0
            },
            "pureTypeSystemProtectedConstructors": {
                "d": 0,
                "DRelative": 0,
                "SRelative": 0,
                "total": 0,
                "s": 0
            },
            "isScript": false,
            "publicField": {
                "d": 0,
                "DRelative": 0,
                "SRelative": 0,
                "total": 0,
                "s": 0
            },
            "pureTypeSystemProtectedMethods": {
                "d": 0,
                "DRelative": 0,
                "SRelative": 0,
                "total": 0,
                "s": 0
            },
            "numberOfPublicConstructors": 0,
            "className": "grails.story.HelloControllerTests",
            "pureTypeSystemPrivateConstructors": {
                "d": 0,
                "DRelative": 0,
                "SRelative": 0,
                "total": 0,
                "s": 0
            },
            "protectedMethodReturn": {
                "d": 0,
                "DRelative": 0,
                "SRelative": 0,
                "total": 0,
                "s": 0
            },
            "publicMethodParameter": {
                "d": 2,
                "DRelative": 1.0,
                "SRelative": 0.0,
                "total": 2,
                "s": 0
            },
            "pureTypeSystemPublicMethods": {
                "d": 1,
                "DRelative": 1.0,
                "SRelative": 0.0,
                "total": 1,
                "s": 0
            },
            "publicConstructorParameter": {
                "d": 0,
                "DRelative": 0,
                "SRelative": 0,
                "total": 0,
                "s": 0
            },
            "publicMethodReturn": {
                "d": 1,
                "DRelative": 0.07692307692307693,
                "SRelative": 0.9230769230769231,
                "total": 13,
                "s": 12
            },
            "protectedField": {
                "d": 0,
                "DRelative": 0,
                "SRelative": 0,
                "total": 0,
                "s": 0
            },
            "numberOfPrivateConstructors": 0,
            "pureTypeSystemPublicConstructors": {
                "d": 0,
                "DRelative": 0,
                "SRelative": 0,
                "total": 0,
                "s": 0
            },
            "numberOfProtectedConstructors": 0
        },
        {
            "privateField": {
                "d": 0,
                "DRelative": 0,
                "SRelative": 0,
                "total": 0,
                "s": 0
            },
            "protectedConstructorParameter": {
                "d": 0,
                "DRelative": 0,
                "SRelative": 0,
                "total": 0,
                "s": 0
            },
            "protectedMethodParameter": {
                "d": 0,
                "DRelative": 0,
                "SRelative": 0,
                "total": 0,
                "s": 0
            },
            "privateMethodParameter": {
                "d": 0,
                "DRelative": 0,
                "SRelative": 0,
                "total": 0,
                "s": 0
            },
            "privateConstructorParameter": {
                "d": 0,
                "DRelative": 0,
                "SRelative": 0,
                "total": 0,
                "s": 0
            },
            "pureTypeSystemPrivateMethods": {
                "d": 0,
                "DRelative": 0,
                "SRelative": 0,
                "total": 0,
                "s": 0
            },
            "privateMethodReturn": {
                "d": 0,
                "DRelative": 0,
                "SRelative": 0,
                "total": 0,
                "s": 0
            },
            "location": "/opt/groovonomics/temp/Jdourd_CodeStory-grails/grails-app/controllers/grails/story/JajascriptTesterController.groovy",
            "localVariable": {
                "d": 6,
                "DRelative": 0.75,
                "SRelative": 0.25,
                "total": 8,
                "s": 2
            },
            "pureTypeSystemProtectedConstructors": {
                "d": 0,
                "DRelative": 0,
                "SRelative": 0,
                "total": 0,
                "s": 0
            },
            "isScript": false,
            "publicField": {
                "d": 0,
                "DRelative": 0,
                "SRelative": 0,
                "total": 0,
                "s": 0
            },
            "pureTypeSystemProtectedMethods": {
                "d": 0,
                "DRelative": 0,
                "SRelative": 0,
                "total": 0,
                "s": 0
            },
            "numberOfPublicConstructors": 0,
            "className": "grails.story.JajascriptTesterController",
            "pureTypeSystemPrivateConstructors": {
                "d": 0,
                "DRelative": 0,
                "SRelative": 0,
                "total": 0,
                "s": 0
            },
            "protectedMethodReturn": {
                "d": 0,
                "DRelative": 0,
                "SRelative": 0,
                "total": 0,
                "s": 0
            },
            "publicMethodParameter": {
                "d": 0,
                "DRelative": 0,
                "SRelative": 0,
                "total": 0,
                "s": 0
            },
            "pureTypeSystemPublicMethods": {
                "d": 0,
                "DRelative": 0,
                "SRelative": 0,
                "total": 0,
                "s": 0
            },
            "publicConstructorParameter": {
                "d": 0,
                "DRelative": 0,
                "SRelative": 0,
                "total": 0,
                "s": 0
            },
            "publicMethodReturn": {
                "d": 2,
                "DRelative": 1.0,
                "SRelative": 0.0,
                "total": 2,
                "s": 0
            },
            "protectedField": {
                "d": 0,
                "DRelative": 0,
                "SRelative": 0,
                "total": 0,
                "s": 0
            },
            "numberOfPrivateConstructors": 0,
            "pureTypeSystemPublicConstructors": {
                "d": 0,
                "DRelative": 0,
                "SRelative": 0,
                "total": 0,
                "s": 0
            },
            "numberOfProtectedConstructors": 0
        },
        {
            "privateField": {
                "d": 0,
                "DRelative": 0,
                "SRelative": 0,
                "total": 0,
                "s": 0
            },
            "protectedConstructorParameter": {
                "d": 0,
                "DRelative": 0,
                "SRelative": 0,
                "total": 0,
                "s": 0
            },
            "protectedMethodParameter": {
                "d": 0,
                "DRelative": 0,
                "SRelative": 0,
                "total": 0,
                "s": 0
            },
            "privateMethodParameter": {
                "d": 0,
                "DRelative": 0,
                "SRelative": 0,
                "total": 0,
                "s": 0
            },
            "privateConstructorParameter": {
                "d": 0,
                "DRelative": 0,
                "SRelative": 0,
                "total": 0,
                "s": 0
            },
            "pureTypeSystemPrivateMethods": {
                "d": 0,
                "DRelative": 0,
                "SRelative": 0,
                "total": 0,
                "s": 0
            },
            "privateMethodReturn": {
                "d": 0,
                "DRelative": 0,
                "SRelative": 0,
                "total": 0,
                "s": 0
            },
            "location": "/opt/groovonomics/temp/Jdourd_CodeStory-grails/grails-app/controllers/grails/story/HelloController.groovy",
            "localVariable": {
                "d": 1,
                "DRelative": 1.0,
                "SRelative": 0.0,
                "total": 1,
                "s": 0
            },
            "pureTypeSystemProtectedConstructors": {
                "d": 0,
                "DRelative": 0,
                "SRelative": 0,
                "total": 0,
                "s": 0
            },
            "isScript": false,
            "publicField": {
                "d": 0,
                "DRelative": 0,
                "SRelative": 0,
                "total": 0,
                "s": 0
            },
            "pureTypeSystemProtectedMethods": {
                "d": 0,
                "DRelative": 0,
                "SRelative": 0,
                "total": 0,
                "s": 0
            },
            "numberOfPublicConstructors": 0,
            "className": "grails.story.HelloController",
            "pureTypeSystemPrivateConstructors": {
                "d": 0,
                "DRelative": 0,
                "SRelative": 0,
                "total": 0,
                "s": 0
            },
            "protectedMethodReturn": {
                "d": 0,
                "DRelative": 0,
                "SRelative": 0,
                "total": 0,
                "s": 0
            },
            "publicMethodParameter": {
                "d": 0,
                "DRelative": 0,
                "SRelative": 0,
                "total": 0,
                "s": 0
            },
            "pureTypeSystemPublicMethods": {
                "d": 0,
                "DRelative": 0,
                "SRelative": 0,
                "total": 0,
                "s": 0
            },
            "publicConstructorParameter": {
                "d": 0,
                "DRelative": 0,
                "SRelative": 0,
                "total": 0,
                "s": 0
            },
            "publicMethodReturn": {
                "d": 1,
                "DRelative": 1.0,
                "SRelative": 0.0,
                "total": 1,
                "s": 0
            },
            "protectedField": {
                "d": 0,
                "DRelative": 0,
                "SRelative": 0,
                "total": 0,
                "s": 0
            },
            "numberOfPrivateConstructors": 0,
            "pureTypeSystemPublicConstructors": {
                "d": 0,
                "DRelative": 0,
                "SRelative": 0,
                "total": 0,
                "s": 0
            },
            "numberOfProtectedConstructors": 0
        },
        {
            "privateField": {
                "d": 0,
                "DRelative": 0,
                "SRelative": 0,
                "total": 0,
                "s": 0
            },
            "protectedConstructorParameter": {
                "d": 0,
                "DRelative": 0,
                "SRelative": 0,
                "total": 0,
                "s": 0
            },
            "protectedMethodParameter": {
                "d": 0,
                "DRelative": 0,
                "SRelative": 0,
                "total": 0,
                "s": 0
            },
            "privateMethodParameter": {
                "d": 0,
                "DRelative": 0,
                "SRelative": 0,
                "total": 0,
                "s": 0
            },
            "privateConstructorParameter": {
                "d": 0,
                "DRelative": 0,
                "SRelative": 0,
                "total": 0,
                "s": 0
            },
            "pureTypeSystemPrivateMethods": {
                "d": 0,
                "DRelative": 0,
                "SRelative": 0,
                "total": 0,
                "s": 0
            },
            "privateMethodReturn": {
                "d": 0,
                "DRelative": 0,
                "SRelative": 0,
                "total": 0,
                "s": 0
            },
            "location": "/opt/groovonomics/temp/Jdourd_CodeStory-grails/grails-app/conf/Config.groovy",
            "localVariable": {
                "d": 0,
                "DRelative": 0,
                "SRelative": 0,
                "total": 0,
                "s": 0
            },
            "pureTypeSystemProtectedConstructors": {
                "d": 0,
                "DRelative": 0,
                "SRelative": 0,
                "total": 0,
                "s": 0
            },
            "isScript": true,
            "publicField": {
                "d": 0,
                "DRelative": 0,
                "SRelative": 0,
                "total": 0,
                "s": 0
            },
            "pureTypeSystemProtectedMethods": {
                "d": 0,
                "DRelative": 0,
                "SRelative": 0,
                "total": 0,
                "s": 0
            },
            "numberOfPublicConstructors": 2,
            "className": "script1378428769180",
            "pureTypeSystemPrivateConstructors": {
                "d": 0,
                "DRelative": 0,
                "SRelative": 0,
                "total": 0,
                "s": 0
            },
            "protectedMethodReturn": {
                "d": 0,
                "DRelative": 0,
                "SRelative": 0,
                "total": 0,
                "s": 0
            },
            "publicMethodParameter": {
                "d": 0,
                "DRelative": 0.0,
                "SRelative": 1.0,
                "total": 1,
                "s": 1
            },
            "pureTypeSystemPublicMethods": {
                "d": 0,
                "DRelative": 0.0,
                "SRelative": 1.0,
                "total": 1,
                "s": 1
            },
            "publicConstructorParameter": {
                "d": 0,
                "DRelative": 0.0,
                "SRelative": 1.0,
                "total": 1,
                "s": 1
            },
            "publicMethodReturn": {
                "d": 1,
                "DRelative": 0.5,
                "SRelative": 0.5,
                "total": 2,
                "s": 1
            },
            "protectedField": {
                "d": 0,
                "DRelative": 0,
                "SRelative": 0,
                "total": 0,
                "s": 0
            },
            "numberOfPrivateConstructors": 0,
            "pureTypeSystemPublicConstructors": {
                "d": 0,
                "DRelative": 0.0,
                "SRelative": 1.0,
                "total": 1,
                "s": 1
            },
            "numberOfProtectedConstructors": 0
        },
        {
            "privateField": {
                "d": 0,
                "DRelative": 0,
                "SRelative": 0,
                "total": 0,
                "s": 0
            },
            "protectedConstructorParameter": {
                "d": 0,
                "DRelative": 0,
                "SRelative": 0,
                "total": 0,
                "s": 0
            },
            "protectedMethodParameter": {
                "d": 0,
                "DRelative": 0,
                "SRelative": 0,
                "total": 0,
                "s": 0
            },
            "privateMethodParameter": {
                "d": 0,
                "DRelative": 0,
                "SRelative": 0,
                "total": 0,
                "s": 0
            },
            "privateConstructorParameter": {
                "d": 0,
                "DRelative": 0,
                "SRelative": 0,
                "total": 0,
                "s": 0
            },
            "pureTypeSystemPrivateMethods": {
                "d": 0,
                "DRelative": 0,
                "SRelative": 0,
                "total": 0,
                "s": 0
            },
            "privateMethodReturn": {
                "d": 0,
                "DRelative": 0,
                "SRelative": 0,
                "total": 0,
                "s": 0
            },
            "location": "/opt/groovonomics/temp/Jdourd_CodeStory-grails/grails-app/conf/ApplicationResources.groovy",
            "localVariable": {
                "d": 0,
                "DRelative": 0,
                "SRelative": 0,
                "total": 0,
                "s": 0
            },
            "pureTypeSystemProtectedConstructors": {
                "d": 0,
                "DRelative": 0,
                "SRelative": 0,
                "total": 0,
                "s": 0
            },
            "isScript": true,
            "publicField": {
                "d": 0,
                "DRelative": 0,
                "SRelative": 0,
                "total": 0,
                "s": 0
            },
            "pureTypeSystemProtectedMethods": {
                "d": 0,
                "DRelative": 0,
                "SRelative": 0,
                "total": 0,
                "s": 0
            },
            "numberOfPublicConstructors": 2,
            "className": "script1378428769412",
            "pureTypeSystemPrivateConstructors": {
                "d": 0,
                "DRelative": 0,
                "SRelative": 0,
                "total": 0,
                "s": 0
            },
            "protectedMethodReturn": {
                "d": 0,
                "DRelative": 0,
                "SRelative": 0,
                "total": 0,
                "s": 0
            },
            "publicMethodParameter": {
                "d": 0,
                "DRelative": 0.0,
                "SRelative": 1.0,
                "total": 1,
                "s": 1
            },
            "pureTypeSystemPublicMethods": {
                "d": 0,
                "DRelative": 0.0,
                "SRelative": 1.0,
                "total": 1,
                "s": 1
            },
            "publicConstructorParameter": {
                "d": 0,
                "DRelative": 0.0,
                "SRelative": 1.0,
                "total": 1,
                "s": 1
            },
            "publicMethodReturn": {
                "d": 1,
                "DRelative": 0.5,
                "SRelative": 0.5,
                "total": 2,
                "s": 1
            },
            "protectedField": {
                "d": 0,
                "DRelative": 0,
                "SRelative": 0,
                "total": 0,
                "s": 0
            },
            "numberOfPrivateConstructors": 0,
            "pureTypeSystemPublicConstructors": {
                "d": 0,
                "DRelative": 0.0,
                "SRelative": 1.0,
                "total": 1,
                "s": 1
            },
            "numberOfProtectedConstructors": 0
        },
        {
            "privateField": {
                "d": 0,
                "DRelative": 0,
                "SRelative": 0,
                "total": 0,
                "s": 0
            },
            "protectedConstructorParameter": {
                "d": 0,
                "DRelative": 0,
                "SRelative": 0,
                "total": 0,
                "s": 0
            },
            "protectedMethodParameter": {
                "d": 0,
                "DRelative": 0,
                "SRelative": 0,
                "total": 0,
                "s": 0
            },
            "privateMethodParameter": {
                "d": 0,
                "DRelative": 0,
                "SRelative": 0,
                "total": 0,
                "s": 0
            },
            "privateConstructorParameter": {
                "d": 0,
                "DRelative": 0,
                "SRelative": 0,
                "total": 0,
                "s": 0
            },
            "pureTypeSystemPrivateMethods": {
                "d": 0,
                "DRelative": 0,
                "SRelative": 0,
                "total": 0,
                "s": 0
            },
            "privateMethodReturn": {
                "d": 0,
                "DRelative": 0,
                "SRelative": 0,
                "total": 0,
                "s": 0
            },
            "location": "/opt/groovonomics/temp/Jdourd_CodeStory-grails/grails-app/conf/spring/resources.groovy",
            "localVariable": {
                "d": 0,
                "DRelative": 0,
                "SRelative": 0,
                "total": 0,
                "s": 0
            },
            "pureTypeSystemProtectedConstructors": {
                "d": 0,
                "DRelative": 0,
                "SRelative": 0,
                "total": 0,
                "s": 0
            },
            "isScript": true,
            "publicField": {
                "d": 0,
                "DRelative": 0,
                "SRelative": 0,
                "total": 0,
                "s": 0
            },
            "pureTypeSystemProtectedMethods": {
                "d": 0,
                "DRelative": 0,
                "SRelative": 0,
                "total": 0,
                "s": 0
            },
            "numberOfPublicConstructors": 2,
            "className": "script1378428769420",
            "pureTypeSystemPrivateConstructors": {
                "d": 0,
                "DRelative": 0,
                "SRelative": 0,
                "total": 0,
                "s": 0
            },
            "protectedMethodReturn": {
                "d": 0,
                "DRelative": 0,
                "SRelative": 0,
                "total": 0,
                "s": 0
            },
            "publicMethodParameter": {
                "d": 0,
                "DRelative": 0.0,
                "SRelative": 1.0,
                "total": 1,
                "s": 1
            },
            "pureTypeSystemPublicMethods": {
                "d": 0,
                "DRelative": 0.0,
                "SRelative": 1.0,
                "total": 1,
                "s": 1
            },
            "publicConstructorParameter": {
                "d": 0,
                "DRelative": 0.0,
                "SRelative": 1.0,
                "total": 1,
                "s": 1
            },
            "publicMethodReturn": {
                "d": 1,
                "DRelative": 0.5,
                "SRelative": 0.5,
                "total": 2,
                "s": 1
            },
            "protectedField": {
                "d": 0,
                "DRelative": 0,
                "SRelative": 0,
                "total": 0,
                "s": 0
            },
            "numberOfPrivateConstructors": 0,
            "pureTypeSystemPublicConstructors": {
                "d": 0,
                "DRelative": 0.0,
                "SRelative": 1.0,
                "total": 1,
                "s": 1
            },
            "numberOfProtectedConstructors": 0
        },
        {
            "privateField": {
                "d": 0,
                "DRelative": 0,
                "SRelative": 0,
                "total": 0,
                "s": 0
            },
            "protectedConstructorParameter": {
                "d": 0,
                "DRelative": 0,
                "SRelative": 0,
                "total": 0,
                "s": 0
            },
            "protectedMethodParameter": {
                "d": 0,
                "DRelative": 0,
                "SRelative": 0,
                "total": 0,
                "s": 0
            },
            "privateMethodParameter": {
                "d": 0,
                "DRelative": 0,
                "SRelative": 0,
                "total": 0,
                "s": 0
            },
            "privateConstructorParameter": {
                "d": 0,
                "DRelative": 0,
                "SRelative": 0,
                "total": 0,
                "s": 0
            },
            "pureTypeSystemPrivateMethods": {
                "d": 0,
                "DRelative": 0,
                "SRelative": 0,
                "total": 0,
                "s": 0
            },
            "privateMethodReturn": {
                "d": 0,
                "DRelative": 0,
                "SRelative": 0,
                "total": 0,
                "s": 0
            },
            "location": "/opt/groovonomics/temp/Jdourd_CodeStory-grails/grails-app/conf/BuildConfig.groovy",
            "localVariable": {
                "d": 0,
                "DRelative": 0,
                "SRelative": 0,
                "total": 0,
                "s": 0
            },
            "pureTypeSystemProtectedConstructors": {
                "d": 0,
                "DRelative": 0,
                "SRelative": 0,
                "total": 0,
                "s": 0
            },
            "isScript": true,
            "publicField": {
                "d": 0,
                "DRelative": 0,
                "SRelative": 0,
                "total": 0,
                "s": 0
            },
            "pureTypeSystemProtectedMethods": {
                "d": 0,
                "DRelative": 0,
                "SRelative": 0,
                "total": 0,
                "s": 0
            },
            "numberOfPublicConstructors": 2,
            "className": "script1378428769428",
            "pureTypeSystemPrivateConstructors": {
                "d": 0,
                "DRelative": 0,
                "SRelative": 0,
                "total": 0,
                "s": 0
            },
            "protectedMethodReturn": {
                "d": 0,
                "DRelative": 0,
                "SRelative": 0,
                "total": 0,
                "s": 0
            },
            "publicMethodParameter": {
                "d": 0,
                "DRelative": 0.0,
                "SRelative": 1.0,
                "total": 1,
                "s": 1
            },
            "pureTypeSystemPublicMethods": {
                "d": 0,
                "DRelative": 0.0,
                "SRelative": 1.0,
                "total": 1,
                "s": 1
            },
            "publicConstructorParameter": {
                "d": 0,
                "DRelative": 0.0,
                "SRelative": 1.0,
                "total": 1,
                "s": 1
            },
            "publicMethodReturn": {
                "d": 1,
                "DRelative": 0.5,
                "SRelative": 0.5,
                "total": 2,
                "s": 1
            },
            "protectedField": {
                "d": 0,
                "DRelative": 0,
                "SRelative": 0,
                "total": 0,
                "s": 0
            },
            "numberOfPrivateConstructors": 0,
            "pureTypeSystemPublicConstructors": {
                "d": 0,
                "DRelative": 0.0,
                "SRelative": 1.0,
                "total": 1,
                "s": 1
            },
            "numberOfProtectedConstructors": 0
        },
        {
            "privateField": {
                "d": 0,
                "DRelative": 0,
                "SRelative": 0,
                "total": 0,
                "s": 0
            },
            "protectedConstructorParameter": {
                "d": 0,
                "DRelative": 0,
                "SRelative": 0,
                "total": 0,
                "s": 0
            },
            "protectedMethodParameter": {
                "d": 0,
                "DRelative": 0,
                "SRelative": 0,
                "total": 0,
                "s": 0
            },
            "privateMethodParameter": {
                "d": 0,
                "DRelative": 0,
                "SRelative": 0,
                "total": 0,
                "s": 0
            },
            "privateConstructorParameter": {
                "d": 0,
                "DRelative": 0,
                "SRelative": 0,
                "total": 0,
                "s": 0
            },
            "pureTypeSystemPrivateMethods": {
                "d": 0,
                "DRelative": 0,
                "SRelative": 0,
                "total": 0,
                "s": 0
            },
            "privateMethodReturn": {
                "d": 0,
                "DRelative": 0,
                "SRelative": 0,
                "total": 0,
                "s": 0
            },
            "location": "/opt/groovonomics/temp/Jdourd_CodeStory-grails/grails-app/conf/DataSource.groovy",
            "localVariable": {
                "d": 0,
                "DRelative": 0,
                "SRelative": 0,
                "total": 0,
                "s": 0
            },
            "pureTypeSystemProtectedConstructors": {
                "d": 0,
                "DRelative": 0,
                "SRelative": 0,
                "total": 0,
                "s": 0
            },
            "isScript": true,
            "publicField": {
                "d": 0,
                "DRelative": 0,
                "SRelative": 0,
                "total": 0,
                "s": 0
            },
            "pureTypeSystemProtectedMethods": {
                "d": 0,
                "DRelative": 0,
                "SRelative": 0,
                "total": 0,
                "s": 0
            },
            "numberOfPublicConstructors": 2,
            "className": "script1378428769447",
            "pureTypeSystemPrivateConstructors": {
                "d": 0,
                "DRelative": 0,
                "SRelative": 0,
                "total": 0,
                "s": 0
            },
            "protectedMethodReturn": {
                "d": 0,
                "DRelative": 0,
                "SRelative": 0,
                "total": 0,
                "s": 0
            },
            "publicMethodParameter": {
                "d": 0,
                "DRelative": 0.0,
                "SRelative": 1.0,
                "total": 1,
                "s": 1
            },
            "pureTypeSystemPublicMethods": {
                "d": 0,
                "DRelative": 0.0,
                "SRelative": 1.0,
                "total": 1,
                "s": 1
            },
            "publicConstructorParameter": {
                "d": 0,
                "DRelative": 0.0,
                "SRelative": 1.0,
                "total": 1,
                "s": 1
            },
            "publicMethodReturn": {
                "d": 1,
                "DRelative": 0.5,
                "SRelative": 0.5,
                "total": 2,
                "s": 1
            },
            "protectedField": {
                "d": 0,
                "DRelative": 0,
                "SRelative": 0,
                "total": 0,
                "s": 0
            },
            "numberOfPrivateConstructors": 0,
            "pureTypeSystemPublicConstructors": {
                "d": 0,
                "DRelative": 0.0,
                "SRelative": 1.0,
                "total": 1,
                "s": 1
            },
            "numberOfProtectedConstructors": 0
        }
    ],
    "name": ""
}